Metadata-Version: 2.4
Name: llm-bedrock-converse
Version: 0.1.0
Summary: LLM plugin for AWS Bedrock Converse API with tool calling and embeddings support
Author-email: geehexx <andrewcrozier86@gmail.com>
License: Apache-2.0
Project-URL: Homepage, https://github.com/geehexx/llm-bedrock-converse
Project-URL: Repository, https://github.com/geehexx/llm-bedrock-converse
Project-URL: Issues, https://github.com/geehexx/llm-bedrock-converse/issues
Classifier: Development Status :: 4 - Beta
Classifier: Intended Audience :: Developers
Classifier: License :: OSI Approved :: Apache Software License
Classifier: Programming Language :: Python :: 3
Classifier: Programming Language :: Python :: 3.8
Classifier: Programming Language :: Python :: 3.9
Classifier: Programming Language :: Python :: 3.10
Classifier: Programming Language :: Python :: 3.11
Classifier: Programming Language :: Python :: 3.12
Requires-Python: >=3.8
License-File: LICENSE
Requires-Dist: llm>=0.19
Requires-Dist: boto3>=1.35.0
Provides-Extra: test
Requires-Dist: pytest>=7.0; extra == "test"
Requires-Dist: pytest-mock>=3.10; extra == "test"
Requires-Dist: pytest-cov>=4.0; extra == "test"
Dynamic: license-file
